Metadata-Version: 2.1
Name: odoo-addon-stock_orderpoint_generator
Version: 17.0.1.0.0.3
Requires-Python: >=3.10
Requires-Dist: odoo>=17.0a,<17.1dev
Summary: Mass configuration of stock order points
Home-page: https://github.com/OCA/stock-logistics-orderpoint
License: AGPL-3
Author: Camptocamp, Tecnativa, Odoo Community Association (OCA)
Author-email: support@odoo-community.org
Classifier: Programming Language :: Python
Classifier: Framework :: Odoo
Classifier: Framework :: Odoo :: 17.0
Classifier: License :: OSI Approved :: GNU Affero General Public License v3
